g42cloudsdkrds/__init__.py
g42cloudsdkrds/v3/__init__.py
g42cloudsdkrds/v3/rds_async_client.py
g42cloudsdkrds/v3/rds_client.py
g42cloudsdkrds/v3/model/__init__.py
g42cloudsdkrds/v3/model/ad_domain_info.py
g42cloudsdkrds/v3/model/allow_db_privilege_request.py
g42cloudsdkrds/v3/model/allow_db_privilege_response.py
g42cloudsdkrds/v3/model/allow_db_user_privilege_request.py
g42cloudsdkrds/v3/model/allow_db_user_privilege_response.py
g42cloudsdkrds/v3/model/allow_sqlserver_db_user_privilege_request.py
g42cloudsdkrds/v3/model/allow_sqlserver_db_user_privilege_response.py
g42cloudsdkrds/v3/model/api_version.py
g42cloudsdkrds/v3/model/apply_configuration_async_request.py
g42cloudsdkrds/v3/model/apply_configuration_async_response.py
g42cloudsdkrds/v3/model/apply_configuration_request.py
g42cloudsdkrds/v3/model/apply_configuration_response_apply_results.py
g42cloudsdkrds/v3/model/attach_eip_request.py
g42cloudsdkrds/v3/model/attach_eip_response.py
g42cloudsdkrds/v3/model/auditlog.py
g42cloudsdkrds/v3/model/available_zone.py
g42cloudsdkrds/v3/model/backup_database.py
g42cloudsdkrds/v3/model/backup_datastore.py
g42cloudsdkrds/v3/model/backup_for_list.py
g42cloudsdkrds/v3/model/backup_info.py
g42cloudsdkrds/v3/model/backup_policy.py
g42cloudsdkrds/v3/model/backup_strategy.py
g42cloudsdkrds/v3/model/backup_strategy_for_response.py
g42cloudsdkrds/v3/model/batch_tag_action_add_request_body.py
g42cloudsdkrds/v3/model/batch_tag_action_del_request_body.py
g42cloudsdkrds/v3/model/batch_tag_add_action_request.py
g42cloudsdkrds/v3/model/batch_tag_add_action_response.py
g42cloudsdkrds/v3/model/batch_tag_del_action_request.py
g42cloudsdkrds/v3/model/batch_tag_del_action_response.py
g42cloudsdkrds/v3/model/bind_eip_request.py
g42cloudsdkrds/v3/model/binlog_clear_policy_request_body.py
g42cloudsdkrds/v3/model/change_failover_mode_request.py
g42cloudsdkrds/v3/model/change_failover_mode_response.py
g42cloudsdkrds/v3/model/change_failover_strategy_request.py
g42cloudsdkrds-0.0.10b0.dist-info/LICENSE
g42cloudsdkrds-0.0.10b0.dist-info/METADATA
g42cloudsdkrds-0.0.10b0.dist-info/WHEEL
g42cloudsdkrds-0.0.10b0.dist-info/top_level.txt
g42cloudsdkrds-0.0.10b0.dist-info/RECORD
